README.rst
setup.py
heidi/__init__.py
heidi.egg-info/PKG-INFO
heidi.egg-info/SOURCES.txt
heidi.egg-info/dependency_links.txt
heidi.egg-info/requires.txt
heidi.egg-info/top_level.txt
heidi/Parse/__init__.py
heidi/Parse/parse.py
heidi/Segmentation/__init__.py
heidi/Segmentation/texttiling.py
heidi/Summarization/__init__.py
heidi/Summarization/clusterrank.py
heidi/Summarization/randomSum.py