Metadata-Version: 1.1
Name: heidi
Version: 1.0.18
Summary: Module for conversational and text summarization and much more
Home-page: http://google.com/
Author: Aditya Chatterjee
Author-email: aditianhacker@gmail.com
License: MIT License
Keywords: cluster rank,text rank,texttiling,data mining,conversation summarization,text summarization,text segmentation,data reduction,NLP,computational linguistics,natural language processing
Platform: UNKNOWN
Classifier: Development Status :: 4 - Beta
Classifier: License :: OSI Approved :: MIT License
Classifier: Intended Audience :: Developers
Classifier: Intended Audience :: Education
Classifier: Intended Audience :: Science/Research
Classifier: Intended Audience :: Other Audience
Classifier: Intended Audience :: End Users/Desktop
Classifier: Natural Language :: English
Classifier: Topic :: Education
Classifier: Topic :: Internet
Classifier: Topic :: Scientific/Engineering :: Information Analysis
Classifier: Topic :: Text Processing :: Filters
Classifier: Topic :: Text Processing :: Linguistic
Classifier: Operating System :: OS Independent
Classifier: Programming Language :: Python
Classifier: Programming Language :: Python :: 2
Classifier: Programming Language :: Python :: 2.7
Classifier: Programming Language :: Python :: 3
Classifier: Programming Language :: Python :: 3.3
Classifier: Programming Language :: Python :: 3.4
Classifier: Programming Language :: Python :: 3.5
Classifier: Programming Language :: Python :: Implementation :: CPython
Classifier: Topic :: Software Development :: Libraries
Classifier: Topic :: Software Development :: Libraries :: Python Modules
Classifier: Topic :: Utilities
